Workbook

Sheet Planilha Custos
A2: PLANILHA DE CUSTOS
A6: Qtde. | B6: Estrutura
A7: 2 | B7: Municípios de Rio Branco e Cruzeiro do Sul | F7: =94*45% -> 42.3
A8: =Escolas!A16 -> 14 | B8: Escola
A9: =Escolas!H17 -> 16 | B9: Professores de Educação Física
A10: =Escolas!E17 -> 14 | B10: Gestores
A11: =Escolas!F17 -> 56 | B11: Coordenadores de Área
A12: =Escolas!G17 -> 14 | B12: Coordenadores de Ensino
A13: =Escolas!D17 -> 7116 | B13: Alunos
A17: LEVANTAMENTO DE DADOS
A18: Itens | B18: Levantamento de Dados | C18: Unidade | D18: quantidade | F18: Valor Unitário | G18: Valor Total
A19: 1 | B19: Levantamento Situacional: Esta etapa compreende a realização de levantamento situacional das Escolas em que o público alvo está matriculado | C19: unidade | D19: 1 | F19: =85000+60000+67310.03 -> 212310.03 | G19: =F19*D19 -> 212310.03
A20: 2 | B20: Protocolo de diagnóstico das capacidades físicas, de saúde, psicossociais e vocação esportiva, com estudos técnicos das métricas e potencilalidade dos alunos de acordo com suas caracteristicas e aptidões esportivas e vocacionais. | C20: Serviço | D20: =A13 -> 7116 | F20: 132 | G20: =D20*F20 -> 939312
A21: 3 | B21: Pesquisa Científica | C21: Serviço | D21: 1 | F21: =334975.29-6926.95 -> 328048.34 | G21: =D21*F21 -> 328048.34
B22: SUB-TOTAL | G22: =SUM(G19:G21) -> 1479670.4
A24: MATERIAIS PEDAGÓGICOS E SISTEMA EAD
A25: Itens | B25: CURSOS DE FORMAÇÃO | C25: Unidade | D25: quantidade | F25: Valor Unitário | G25: Valor Total
A26: 4 | B26: Apresentação Metodologia (Presencial - Carga Horária 4 horas) | C26: disponibilizaçao de curso | D26: =A9+A10+A11+A12 -> 100 | F26: 250 | G26: =D26*F26 -> 25000
A27: 5 | B27: Tecnologia e Desenvolvimento Talentos Esportivo (EAD / Carga Horária de 40 Horas) | C27: disponibilizaçao de curso | D27: =A9+A10 -> 30 | F27: 250 | G27: =D27*F27 -> 7500
A28: 6 | B28: Promoção e Defesa dos Direitos da Criança e do Adolescente (EAD / Carga Horária de 40 Horas) | C28: disponibilizaçao de curso | D28: =A9+A10 -> 30 | F28: 250 | G28: =D28*F28 -> 7500
A29: 7 | B29: Temas Transversais (Agenda 2030 – ODS/ONU e BNCC) (EAD / Carga Horária de 40 Horas) - PROFESSORES | C29: disponibilizaçao de curso | D29: =A9+A10 -> 30 | F29: 250 | G29: =D29*F29 -> 7500
A30: 8 | B30: Temas Transversais (Agenda 2030 – ODS/ONU e BNCC) (EAD / Carga Horária de 40 Horas) - ALUNOS | C30: disponibilizaçao de curso | D30: =A13*25% -> 1779 | F30: 250 | G30: =D30*F30 -> 444750
A31: 9 | B31: Pós-Graduação em Detecção e Desenvolvimento de Talentos Esportivos na Infância e Adolescência – Reconhecido pelo MEC. (EAD / Carga Horária de 360 Horas). | C31: disponibilizaçao de curso | D31: =A9+A10 -> 30 | F31: 2800 | G31: =D31*F31 -> 84000
A32: 10 | B32: Oficinas de Qualificação Social | C32: disponibilizaçao de curso | D32: 1500 | F32: 250 | G32: =D32*F32 -> 375000
A33: 11 | B33: Palestras de Capacitação | C33: diária | D33: 6 | E33: 2 | F33: 5000 | G33: =D33*F33 -> 30000
A34: 12 | B34: Palestrante Regional: Palestras de conscientização/motivacionais nas escolas | C34: diária | D34: =A8*3 -> 42 | F34: 1500 | G34: =D34*F34 -> 63000
A35: 13 | B35: A Olimpíada do Saber, Esporte e Educação: Plataforma para estudantes das escolas participantes, atividades de gamificação para estimular a competição saudável e o aprimoramento acadêmico, interativo para engajamento dos alunos. Aplicação de testes/ provas que abordarão temas ligados às mais diversas modalidades esportivas, bem como suas correlações com diversas áreas do conhecimento. | C35: Disponibilização | D35: 1 | F35: 259730 | G35: =D35*F35 -> 259730
A36: 14 | B36: Cursos Preparatório para Pré-Vestibular | C36: disponibilizaçao de curso | D36: =A13*25% -> 1779 | F36: 250 | G36: =D36*F36 -> 444750
A37: 15 | B37: Curso de Educação Financeira | C37: disponibilizaçao de curso | D37: 1500 | F37: 250 | G37: =D37*F37 -> 375000
B38: TOTAL FORMAÇÃO | G38: =SUM(G26:G37) -> 2123730
A40: SISTEMA DE TECNOLOGIA
A41: Itens | B41: Sistema Tecnológico | C41: Unidade | D41: quantidade | F41: Valor Unitário | G41: Valor Total
A42: 17 | B42: Sistema de gestão da Informação e Indicadores Sociais. Plataformas digitais e Business Intelligence (B.I.) aptas à coleta e interpretação de métricas relacionadas as escolas de EMTI, bem como do acompanhamento sistemático dos alunos, garantindo que as informações não se percam e sejam de fácil acesso para ambas as partes; | C42: serviço | D42: 1 | F42: =A13*5.1*12 -> 435499.2 | G42: =F42*D42 -> 435499.2
A43: 18 | B43: Impressão de Carteirinha para identificação dos alunos. Produzida em PVC compactado 4/4 cores de 1mm. | C43: serviço | D43: =A13 -> 7116 | F43: 12.5 | G43: =D43*F43*2 -> 177900
B44: SUB-TOTAL | G44: =SUM(G42:G43) -> 613399.2
A46: AQUISIÇÃO DE MATERIAIS E EQUIPAMENTOS
A48: MATERIAIS ESPORTIVOS
A49: Itens | B49: MATERIAIS ESPORTIVOS | C49: Unidade | D49: quantidade | F49: Valor Unitário | G49: Valor Total
A50: 19 | B50: Bola de Basquete Adulto - Bola oficial de basquetebol, tamanho masculino, matrizada, confeccionada com borracha, câmara airbility, miolo slip system removível e lubrifica do tamanho 7 com 74,9 cm de diâmetro, pesando entre 567 e 624 gramas, | C50: UNI | D50: =$A$8*6 -> 84 | F50: 129.9 | G50: =D50*F50 -> 10911.6
A51: 20 | B51: Bola de Basquete Infantil Bola de Basquete (tamanho mirim), matrizada, confeccionada em borracha, câmara de ar em butil miolo de válvula removível peso aproximado: 300 a 500 gramas, Medida aproximada de circunferência 60 a 74cm. | C51: UNI | D51: =$A$8*6 -> 84 | F51: 129.9 | G51: =D51*F51 -> 10911.6
A52: 21 | B52: Bola oficial 500 - Futsal Confeccionada em poliuretano. Diâmetro 61 - 64 cm, Peso 410- 440 G, Câmera Airbility feita em borracha butílica e Miolo Slip System removível e lubrificado, Termotec, absorção de água é de 0%, Material de alta qualidade no revestimento, no reforço e na câmara de ar para desempenho perfeito. | C52: UNI | D52: =$A$8*6 -> 84 | F52: 149.9 | G52: =D52*F52 -> 12591.6
A53: 22 | B53: Bola oficial 200 -Futsal Confeccionada em poliuretano. Diâmetro 59-55cm, Peso 350-380G, câmera Airbility e Miolo Slip System removível, lubrificado, Termotec, com 0% absorção de água, alta durabilidade e maciez extra, Material de alta qualidade no revestimento, no reforço e na câmara de ar para desempenho perfeito. | C53: UNI | D53: =$A$8*6 -> 84 | F53: 149.9 | G53: =D53*F53 -> 12591.6
A54: 23 | B54: Bola de Handebol Adulto H3L, adulto masculino, costurada, com 32 gomos, confeccionada em PU ultra grip, miolo slip system removível e lubrificado, câmara arbility. Circunferência 58 a 60 cm, 425 a 475 g de peso. | C54: UNI | D54: =$A$8*6 -> 84 | F54: 189.9 | G54: =D54*F54 -> 15951.6
A55: 24 | B55: Bola de Handebol Infantiil h 1l trinta e dois gomos, costurada, confeccionada em pvc ou pu, diâmetro 49 a 51 cm, peso 230 a 270 gramas, câmara airbility, miolo slip system removível. | C55: UNI | D55: =$A$8*6 -> 84 | F55: 189.9 | G55: =D55*F55 -> 15951.6
A56: 25 | B56: Bola voleibol, material: microfibra, peso cheia: 325 a 400 g, circunferência: 65 a 67 cm, características adicionais: matrizada, com miolo substituível, pressão: 03 - 04 lb, aplicação: volei de quadra, | C56: UNI | D56: =$A$8*6 -> 84 | F56: 189.9 | G56: =D56*F56 -> 15951.6
A57: 26 | B57: Bola de Vôlei Infantil TIPO 7.0 OU SIMILAR; Material: Sem Costura, Composição: PVC, Peso Aproximado: 260-280 gramas, Circunferência aproximada: 65 - 67 cm, Sistema: atrizada, Miolo removível e Lubrificado, Câmara Internal Latex, Indicado para : Jogo. | C57: UNI | D57: =$A$8*6 -> 84 | F57: 189.9 | G57: =D57*F57 -> 15951.6
A58: 27 | B58: Par de rede de Basquete - Descrição: Material: Fio Seda, Cor: Branca, Aplicação: Basquete, Características Adicionais: Malha Poliéster, Nó Duplo, Alta Resistência, Modelo: Oficial | C58: PAR | D58: =$A$8*2 -> 28 | F58: 69.9 | G58: =D58*F58 -> 1957.2
A59: 28 | B59: Par de rede para Trave de Gol Futsal/handball -Fio 2mm Nylon. Dimensões: 3,20m na largura, 2,10m de altura, 0,40m de recuo superior e 0,80m de recuo inferior; | C59: PAR | D59: =$A$8*2 -> 28 | F59: 269.9 | G59: =D59*F59 -> 7557.2
A60: 29 | B60: REDE DE VOLEI Oficial Confeccionada em fio de polipropileno com 2,0mm de espessura. Malha: 10 x 10cm. 2 lonas de algodão. Acom panha cordas laterais para instalação. Acompanha cabo de aço. Medida: 9,50 x 1,00 m | C60: UNI | D60: =$A$8*2 -> 28 | F60: 299.9 | G60: =D60*F60 -> 8397.2
A61: 30 | B61: Cone de plástico tipo chapéu chinês, composto em PVC. Material resistente, leve e flexível. Tamanho: 20- 25 cm, Cor | C61: UNI | D61: =$A$8*6 -> 84 | F61: 9.9 | G61: =D61*F61 -> 831.6
A62: 31 | B62: Cone para treino. Material: Borracha Sintética Flexível, Tamanho: 20- 25 cm, Cor: À escolher | C62: UNI | D62: =$A$8*6 -> 84 | F62: 12.9 | G62: =D62*F62 -> 1083.6
A63: 32 | B63: Bomba para encher bola, FABRICADA EM POLIPROPILENO (PP) RESISTENTE, COM TECNOLOGIA "DOUBLE ACTION" E BICO | C63: UNI | D63: =$A$8*3 -> 42 | F63: 59.9 | G63: =D63*F63 -> 2515.8
A64: 33 | B64: Apito profissional bocal de silicone. Alta intensidade, com dedal e bocal de silicone. Feito em polipropileno. | C64: UNI | D64: =$A$8*6 -> 84 | F64: 29.9 | G64: =D64*F64 -> 2511.6
A65: 34 | B65: Rede para guardar bolas. Material: Nylon. Características: com cordão de aperto deslizante. Capacidade: 10 a 14 bolas | C65: UNI | D65: =$A$8*3 -> 42 | F65: 59.9 | G65: =D65*F65 -> 2515.8
A66: 35 | B66: Corda de Pular Indicado para : Treinamento, ganho de Força e Resistência Muscular, auxilia Emagrecimento, condicionamento Físico, material:PVC, composição: Corda em PVC, manopla de espuma, dimensões Aproximadas: 2,75cm, importante: Sem Rolamento | C66: UNI | D66: =$A$8*6 -> 84 | F66: 39.9 | G66: =D66*F66 -> 3351.6
A67: 36 | B67: Peteca oficial - o diâmetro da base da peteca deve ter de 5 cm a 5,2 cm e sua altura deve ser de 20 cm incluindo as penas. o peso da peteca deve ser de 40 a 42 gramas, aproximadamente.as penas devem ser em número de quatro, montadas paralelamente duas a duas, de modo que o quadrado formado caiba num círculo ideal com diâmetro de 4 cm a 5 cm.as penas preferencialmente brancas, porém, podem ter outra coloração.a base deve ser construída com di scos de borracha, montados em camadas sobrepostas. macia, mais rápida e precisa; maior resistência e durabilidade; presilha plástica que permite a padroniz ação e o alinhamento perfeito das penas. selo branco para visualização em jogos noturnos | C67: UNI | D67: =$A$8*6 -> 84 | F67: 29.9 | G67: =D67*F67 -> 2511.6
A68: 37 | B68: Jogo de Colete de Identificação c/ 12 unidades - CONJUNTO - Colete Material: 100% Poliéster , Modelo: Dupla Face , Tamanho: Único , Uso: Tático , silkado | C68: CONJUTO | D68: =$A$8*6 -> 84 | F68: 479.9 | G68: =D68*F68 -> 40311.6
A69: 38 | B69: Aquisição de Cronometro digital: Contagem regressiva e progressiva com alarme; Alarme visual e sonoro ajustável; Programação de 1 segundo a 99 horas, 59 minutos e 59 segundos; Resolução: 1/100 segundos; ; Acompanhado de bateria de 1.5 VL. Dimensões: 61 x 71 x 25 mm; | C69: UNIDADES | D69: =$A$8*3 -> 42 | F69: 129.9 | G69: =D69*F69 -> 5455.8
A70: 39 | B70: Kit com 8 estacas de agilidade com base, 1,60mts de altura, para treino, sem molas | C70: KIT | D70: =$A$8*2 -> 28 | F70: 599 | G70: =D70*F70 -> 16772
A71: 40 | B71: Escada de agilidade, descrição aproximada :confeccionada com material nylon e polipropileno, com 10 degraus | C71: UNI | D71: =$A$8*2 -> 28 | F71: 149.9 | G71: =D71*F71 -> 4197.2
A72: 41 | B72: Tabuleiro xadrez escolar -, material:madeira, tipo xadrez, aplicação:lazer e entretenimento, características adicionais com peças plásticas | C72: UNI | D72: =$A$8*4 -> 56 | F72: 89.9 | G72: =D72*F72 -> 5034.4
A73: 42 | B73: Tabuleiro de dama escolar- com 24 peças, tabuleiro em madeira mdf/MADEIRA; em dimensões mínimas 26cm x 26cm; (12 peças plásticas brancas e 12 peças pretas) | C73: UNI | D73: =$A$8*4 -> 56 | F73: 79.9 | G73: =D73*F73 -> 4474.4
A74: 43 | B74: Placar – pvc rígido com sistema articulado. peso: 942g aproximadamente. dimensões(axlxp) montado: 22x39x19cm. ideal para futsal, tênis de mesa e vôlei. material bemresistente ou similar | C74: UNI | D74: =$A$8 -> 14 | F74: 295 | G74: =D74*F74 -> 4130
A75: 44 | B75: Par Poste de Vôlei Oficial, aprovado pela Confederação Brasileira de Voleibol (CBV), Perfil tubular metálico em aço carbono, com espessura mínima de 2 mm, no mínimo 2,55m de altura, na cor branca. Com um sistema ágil de regulagem e ajuste para todas as categorias, com Regulador telescópico, Catraca (cremalheira) em ferro fundido com manivela para regulagem da rede. Buchas de espera em PVC e rebaixo de superfície para receber a tampa de aço a nível do piso. Ganchos de segurança para rede | C75: PAR | D75: =$A$8 -> 14 | F75: 3990 | G75: =D75*F75 -> 55860
A76: 45 | B76: Colchonete para ginástica confeccionado em espuma d-23, revestimento em bagum azul ou preto ou material similar, med aproximada .0,90x0,50x0,03m | C76: uni | D76: =$A$8*6 -> 84 | F76: 69.9 | G76: =D76*F76 -> 5871.6
A77: 46 | B77: Arco Bambolê ) Material: Plástico , Diâmetro APROXIMADO: 0,63 M A 0,75, Aplicação: Práticas Esportivas | C77: uni | D77: =$A$8*10 -> 140 | F77: 12.9 | G77: =D77*F77 -> 1806
B78: SUB-TOTAL | G78: =SUM(G50:G77) -> 287959
B79: MATERIAIS ESPORTIVOS PARA AVALIAÇÃO DE ALUNOS
A80: Itens | B80: MATERIAIS DE AVALIAÇÃO | C80: Unidade | D80: quantidade | F80: Valor Unitário | G80: Valor Total
A81: 47 | B81: Tablet: 8,7" Polegadas, 64GB, 4GB RAM,Android 13.0 Octa-core Wi-Fi 4G | C81: unidade | D81: =3*5 -> 15 | F81: 1133.67 | G81: =F81*D81 -> 17005.05
A82: 48 | B82: Trena de Fita de 30 mts arco aberto | C82: unidade | D82: =3*4 -> 12 | F82: 79.9 | G82: =F82*D82 -> 958.8
A83: 49 | B83: Trena de Fita de 05 metros | C83: unidade | D83: =3*4 -> 12 | F83: 29.9 | G83: =F83*D83 -> 358.8
A84: 50 | B84: Colchonete unisex para treinamento | C84: unidade | D84: =3*4 -> 12 | F84: 69.9 | G84: =F84*D84 -> 838.8
A85: 51 | B85: Fita Métrica Corporal | C85: unidade | D85: =3*4 -> 12 | F85: 39.9 | G85: =F85*D85 -> 478.8
A86: 52 | B86: Cronômetro digital profissional eletrônico - Mostrador com 2 Linhas- Relógio.- Alarme.- Despertador.- Memória 100 voltas. Produto Importado. | C86: unidade | D86: =3*6 -> 18 | F86: 129.9 | G86: =F86*D86 -> 2338.2
A87: 53 | B87: Apito profissional bocal de silicone. Alta intensidade, com dedal e bocal de silicone. Feito em polipropileno. | C87: unidade | D87: =3*6 -> 18 | F87: 29.9 | G87: =F87*D87 -> 538.2
A88: 54 | B88: KIT de Cones Agilidade - 06 unidades - Material: Plástico Flexivel - Medida(AxL): 23 cm | C88: unidade | D88: =3*6 -> 18 | F88: 77.4 | G88: =F88*D88 -> 1393.2
A89: 55 | B89: Banco de Wells Portátil Matéria Prima: Alumínio e MDF com Revestimento - Dobrável, facilita o transporte - Portátil - Exclusivo sistema que permite a leitura do resultado diretamente no banco, sem uso de tabelas. - Fixação do suporte inferior magnetizado - Suporte de medição retrátil - Acompanha bolsa para transporte | C89: unidade | D89: =3*3 -> 9 | F89: 1099 | G89: =F89*D89 -> 9891
A90: 56 | B90: Estadiômetro Profissional Portátil - Matéria Prima: Alumínio Capacidade de Medição: 115 cm a 210 cm Tolerância: ±2 mm em 210 cm - Resolução: milímetros | C90: unidade | D90: =3*3 -> 9 | F90: 1099 | G90: =F90*D90 -> 9891
A91: 57 | B91: Balança Evolution Profissional Indicação de classificação de peso Função de acionamento automático Função de desligamento automático Função de pesagem rápida Visor de LCD Black Light Alimentação: 04 pilhas AA - inclusas Visor de LCD 13,5' (O maior da categoria) Visor Black LightPeso da balança: Aproximadamente 2,015Kg - Tamanho da Balança: 35,5 x 34,5 x 3,5Cm | C91: unidade | D91: =3*3 -> 9 | F91: 199.9 | G91: =F91*D91 -> 1799.1
A92: 58 | B92: Dinamômetro de Pressão Manual Profissional Unidade de medidad kg/f Captura automática da força máxima/armazenamento e releitura de resultados para diferentes usuários/design ergonômico/capacidade máxima: 90kg/198lb/divisão: 0.1kg/0.2lb/alimentação: 2x1.5v baterias AAA/exatidão:+-0.5kg/1lb/Ambiente de operação: temperatura 0~35° C;umidade relativa 30~90% U.R | C92: unidade | D92: =3*3 -> 9 | F92: 2499 | G92: =F92*D92 -> 22491
A93: 59 | B93: Prancheta MDF A5 - Prendedor Wire ClipREF.: 110.0Prancheta em Madeira, possui um ótimo acabamento dos dois lados, com os cantos arredondados e prendedor metálico wire, mais moderno e eficiente. | C93: unidade | D93: =3*15 -> 45 | F93: 19.9 | G93: =F93*D93 -> 895.5
A94: 60 | B94: Oxímetro de dedo medidor saturação de oxigênio - Monitora os batimentos cardíacos e a oxigenação do sangue. Possui display digital. Autonomia de 20 horas de medição contínua com duas pilhas padrão AAA. | C94: unidade | D94: =3*3 -> 9 | F94: 199.9 | G94: =F94*D94 -> 1799.1
B95: SUB-TOTAL | G95: =SUM(G81:G94) -> 70676.55
A96: UNIFORMES / BRINDES
A97: Itens | B97: UNIFORMES / BRINDES | C97: Unidade | D97: quantidade | F97: Valor Unitário | G97: Valor Total
A98: 61 | B98: Brindes: Lapís estilizado com referência ao programa e esportes - Corpo redondo em madeira; Traço HB; Adereço de Borracha/plástico ou material similar no topo em formato de itens esportivos | C98: unidade | D98: =$A$13 -> 7116 | F98: 2.2 | G98: =D98*F98 -> 15655.2
A99: 62 | B99: Brinde: Chaveiro Personalizado em formato de bolas (diversas modalidades) | C99: unidade | D99: =$A$13 -> 7116 | F99: 4.5 | G99: =D99*F99 -> 32022
A100: 63 | B100: Camisetas Personalizadas Alunos - camiseta confeccionada em malha pp 100% poliéster na cor branca, gola redonda, barra nas mangas, silk conforme layout, tamanho infantil e adulto | C100: unidade | D100: =$A$13 -> 7116 | F100: 29.9 | G100: =D100*F100 -> 212768.4
A101: 64 | B101: Camisetas Personalizadas Professores: estilo polo para professores de educação física personalizada - equipe itinerante | C101: unidade | D101: =27*5 -> 135 | F101: 52.9 | G101: =D101*F101 -> 7141.5
B102: SUB-TOTAL | G102: =SUM(G98:G101) -> 267587.1
B103: TOTAL COMPRA DE MATERIAIS | G103: =G102+G95+G78 -> 626222.65
A105: CAMPANHA SOCIAL
A106: Itens | B106: COMUNICAÇÃO SOCIAL | C106: Unidade | D106: quantidade | F106: Valor Unitário | G106: Valor Total
A107: 65 | B107: Comunicação: Divulgação e sensibilização do público, desenvolvimento de conceito e criação layout, diagramação e finalização de peças publicitárias, criação de roteiros de vídeos e spots para rádio | C107: serviço | D107: unidade | E107: 1 | F107: =135000+13000 -> 148000 | G107: =E107*F107 -> 148000
A108: 66 | B108: Assessoria Imprensa: Contratação pessoa jurídica - Assessoria de imprensa para envio de (release) informações em formato de texto, ou áudio quando enviado para rádio, follow up com repórteres e editores com o objetivo de oferecer uma pauta sobre o assunto. | C108: mês | D108: unidade | E108: 1 | F108: =6000*12 -> 72000 | G108: =E108*F108 -> 72000
A109: 67 | B109: Ciração e produção de vídeo isntitucional – Captação de imagens, locução, trilha branca, edição, montagem, pós-produção com motion, ajustes de cores e finalizações e demais componentes correlatos. | C109: serviço | D109: unidade | E109: 1 | F109: 82500 | G109: =E109*F109 -> 82500
A110: 68 | B110: Impressão de Banner em Lona vinílica, 180gr, com impressão 4/0, no formato 0,9 x 1,2m, acabamento ilhóis. | C110: serviço | D110: unidade | E110: =A8*4 -> 56 | F110: 315.25 | G110: =F110*E110 -> 17654
A111: 69 | B111: Impressão de Faixa de Divulgação em Lona vinílica, 180gr, com impressão 4/0, no formato 3,0 x 0,8m, com acabamento em ilhóis. | C111: serviço | D111: unidade | E111: =A8*4 -> 56 | F111: 315.25 | G111: =F111*E111 -> 17654
A112: 70 | B112: Impressão Cartilhas - Alunos / Familia. Capa e miolo papel couchê 90g - 12 Páginas, Formato (cm) 20.5 x 27.5 cm, 4 x 4 cores - frente e verso - Alceada e grampeada | C112: serviço | D112: unidade | E112: =A13 -> 7116 | F112: 12.5 | G112: =E112*F112 -> 88950
...

Sheet Cronograma
A2: CRONOGRAMA DE DESEMBOLSO
A4: AÇÕES | B4: 1ª DESEMBOLSO | C4: 2ª DESEMBOLSO | D4: 3ª DESEMBOLSO | E4: 4ª DESEMBOLSO | F4: 5ª DESEMBOLSO | G4: 6ª DESEMBOLSO | H4: 7ª DESEMBOLSO | I4: 8ª DESEMBOLSO | J4: 9ª DESEMBOLSO | K4: 10ª DESEMBOLSO | L4: 11ª DESEMBOLSO | M4: 12ª DESEMBOLSO | N4: TOTAL
A6: LEVANTAMENTO DE DADOS
A7: Levantamento Situacional | C7: ='Planilha Custos'!G19/2 -> 106155.01 | D7: =C7 -> 106155.01 | N7: =SUM(B7:M7) -> 212310.03
A8: Protocolo Avaliativo | D8: ='Planilha Custos'!G20/2 -> 469656 | E8: =D8 -> 469656 | N8: =SUM(B8:M8) -> 939312
A9: Pesquisa Científica | B9: ='Planilha Custos'!G21/12 -> 27337.362 | C9: =B9 -> 27337.362 | D9: =C9 -> 27337.362 | E9: =D9 -> 27337.362 | F9: =E9 -> 27337.362 | G9: =F9 -> 27337.362 | H9: =G9 -> 27337.362 | I9: =H9 -> 27337.362 | J9: =I9 -> 27337.362 | ... M9: =L9 -> 27337.362 | N9: =SUM(B9:M9) -> 328048.34
N10: =SUM(B10:M10) -> 0
A11: MATERIAIS PEDAGÓGICOS E SISTEMA EAD | G11: =B11 -> 0 | N11: =SUM(B11:M11) -> 0
A12: Apresentação da Metodologia | B12: ='Planilha Custos'!G26 -> 25000 | N12: =SUM(B12:M12) -> 25000
A13: Tecnologia e Desenvolvimento Talentos | B13: ='Planilha Custos'!G27 -> 7500 | N13: =SUM(B13:M13) -> 7500
A14: Promoção e Defesa dos Direitos da Criança | B14: ='Planilha Custos'!G28 -> 7500 | N14: =SUM(B14:M14) -> 7500
A15: Temas Transversais - Professores | B15: ='Planilha Custos'!G29 -> 7500 | N15: =SUM(B15:M15) -> 7500
A16: Pós-Gradução | B16: ='Planilha Custos'!G31 -> 84000 | N16: =SUM(B16:M16) -> 84000
A17: Palestra Capacitação | B17: 5000 | D17: 5000 | F17: 5000 | H17: 5000 | J17: 5000 | L17: 5000 | N17: =SUM(B17:M17) -> 30000
A18: Palestrante Regional | E18: ='Planilha Custos'!G34/4 -> 15750 | G18: =E18 -> 15750 | I18: =G18 -> 15750 | L18: =I18 -> 15750 | N18: =SUM(B18:M18) -> 63000
A19: Olimpíadas do Saber | B19: ='Planilha Custos'!G35 -> 259730 | N19: =SUM(B19:M19) -> 259730
A20: Oficinas de Qualificação Social | B20: ='Planilha Custos'!G32 -> 375000 | N20: =SUM(B20:M20) -> 375000
A21: Temas Transversais - Alunos | B21: ='Planilha Custos'!G30 -> 444750 | N21: =SUM(B21:M21) -> 444750
A22: ='Planilha Custos'!B36 -> Cursos Preparatório para Pré-Vestibular | B22: ='Planilha Custos'!G36 -> 444750 | N22: =SUM(B22:M22) -> 444750
A23: ='Planilha Custos'!B37 -> Curso de Educação Financeira | B23: ='Planilha Custos'!G37 -> 375000 | N23: =SUM(B23:M23) -> 375000
A24: Materiais Pegagógicos | B24: =('Planilha Custos'!F168)/3 -> 410949 | E24: =B24*2 -> 821898 | N24: =SUM(B24:M24) -> 1232847
N25: =SUM(B25:M25) -> 0
A26: SISTEMA TECNOLOGIA | N26: =SUM(B26:M26) -> 0
A27: Sistema de Gestão | B27: ='Planilha Custos'!G44 -> 613399.2 | N27: =SUM(B27:M27) -> 613399.2
N28: =SUM(B28:M28) -> 0
A29: AQUISIÇÃO DE MATERIAIS | N29: =SUM(B29:M29) -> 0
A30: Materiais Esportivos | C30: ='Planilha Custos'!G78 -> 287959 | N30: =SUM(B30:M30) -> 287959
A31: Materiais para Avaliação do Alunos | C31: ='Planilha Custos'!G95 -> 70676.55 | N31: =SUM(B31:M31) -> 70676.55
A32: Kit Alunos | C32: ='Planilha Custos'!G102 -> 267587.1 | N32: =SUM(B32:M32) -> 267587.1
N33: =SUM(B33:M33) -> 0
A34: CAMPANHA SOCIAL | N34: =SUM(B34:M34) -> 0
A35: Comunicação | C35: ='Planilha Custos'!G107 -> 148000 | N35: =SUM(C35:M35) -> 148000
A36: Assessoria de Imprensa | B36: ='Planilha Custos'!G108/12 -> 6000 | C36: =B36 -> 6000 | D36: =C36 -> 6000 | E36: =D36 -> 6000 | F36: =E36 -> 6000 | G36: =F36 -> 6000 | H36: =G36 -> 6000 | I36: =H36 -> 6000 | J36: =I36 -> 6000 | ... M36: =L36 -> 6000 | N36: =SUM(B36:M36) -> 72000
A37: Criação e produção de vídeo institucional | E37: ='Planilha Custos'!G109 -> 82500 | N37: =SUM(B37:M37) -> 82500
A38: Materiais Gráficos (impressões) | C38: ='Planilha Custos'!G112+'Planilha Custos'!G113+'Planilha Custos'!G114+'Planilha Custos'!G115+'Planilha Custos'!G116+'Planilha Custos'!G117+('Planilha Custos'!G118/2)+('Planilha Custos'!G119/2)+('Planilha Custos'!G120/3) -> 301510.4 | E38: =('Planilha Custos'!G110/2)+('Planilha Custos'!G111/2) -> 17654 | H38: =E38+('Planilha Custos'!G119/2)+('Planilha Custos'!G118/2)+('Planilha Custos'!G120/3) -> 218325.2 | K38: ='Planilha Custos'!G120/3 -> 8539.2 | N38: =SUM(B38:M38) -> 546028.8
A39: Evento Lançamento Programa | C39: ='Planilha Custos'!G131 -> 166266.1 | N39: =SUM(B39:M39) -> 166266.1
N40: =SUM(B40:M40) -> 0
A41: EVENTOS ESPORTIVOS | N41: =SUM(B41:M41) -> 0
A42: Eventos Esportivos/Logística | E42: =('Planilha Custos'!G135)/3 -> 62011.46 | H42: =E42 -> 62011.46 | K42: =H42 -> 62011.46 | N42: =SUM(B42:M42) -> 186034.38
A43: Logística | B43: ='Planilha Custos'!G147/12 -> 40833.333 | C43: =B43 -> 40833.333 | D43: =C43 -> 40833.333 | E43: =D43 -> 40833.333 | F43: =E43 -> 40833.333 | G43: =F43 -> 40833.333 | H43: =G43 -> 40833.333 | I43: =H43 -> 40833.333 | J43: =I43 -> 40833.333 | ... M43: =L43 -> 40833.333 | N43: =SUM(B43:M43) -> 490000
N44: =SUM(B44:M44) -> 0
A45: RECURSOS HUMANOS | N45: =SUM(B45:M45) -> 0
A46: Equipe de Recursos Huamos | B46: =1354874.94/12 -> 112906.24 | C46: =B46 -> 112906.24 | D46: =C46 -> 112906.24 | E46: =D46 -> 112906.24 | F46: =E46 -> 112906.24 | G46: =F46 -> 112906.24 | H46: =G46 -> 112906.24 | I46: =H46 -> 112906.24 | J46: =I46 -> 112906.24 | ... M46: =L46 -> 112906.24 | N46: =SUM(B46:M46) -> 1354874.9
B48: =SUM(B6:B47) -> 3247155.1 | C48: =SUM(C6:C47) -> 1535231.1 | D48: =SUM(D6:D47) -> 767887.96 | E48: =SUM(E6:E47) -> 1656546.4 | F48: =SUM(F6:F47) -> 192076.94 | G48: =SUM(G6:G47) -> 202826.94 | H48: =SUM(H6:H47) -> 472413.6 | I48: =SUM(I6:I47) -> 202826.94 | ... N48: =SUM(N6:N47) -> 9121573.4
B49: =SUM(B48:D48) -> 5550274.2 | E49: =SUM(E48:G48) -> 2051450.3 | H49: =SUM(H48:J48) -> 867317.48 | K49: =SUM(K48:M48) -> 652531.48
B50: 1º TRIMESTRE | E50: 2º TRIMESTRE | H50: 3º TRIMESTRE | K50: 4º TRIMESTRE
B51: Previsão de Pagamento: 15/05/2025 | E51: Previsão de Pagamento: 15/08/2025 | H51: Previsão de Pagamento: 15/11/2025 | K51: Previsão de Pagamento: 15/02/2026
B52: =B49/N48 -> 0.60847772 | E52: =E49/N48 -> 0.22490092 | H52: =H49/N48 -> 0.095084196 | K52: =K49/N48 -> 0.071537162 | N52: =SUM(B52:M52) -> 1
B53: =(B49+E49)/N48 -> 0.83337864 | H53: =(H49+K49)/N48 -> 0.16662136

Sheet RH - Equipe Técnica
B6: ITENS | C6: EQUIPE DE PROFISSIONAIS | D6: QTDE. PROFISSIONAIS
B7: 1 | C7: Gestor de Projetos | D7: 1
B8: 2 | C8: Coordenador Regional | D8: 1
B9: 3 | C9: Coordenador Metodologia (Educação Física) | D9: 1
B10: 4 | C10: Coordenador Pedagógico | D10: 1
C11: EQUIPE MULTIDISCIPLINAR
B12: 5 | C12: Coordenador Metodologia (Educação Física) | D12: 3
B13: 6 | C13: Pedagogo | D13: 2
B14: 7 | C14: Psicólogo | D14: 2
B15: 8 | C15: Assistente Social | D15: 2
B16: 9 | C16: Nutricionista | D16: 2
B17: 10 | C17: Dentista | D17: 2
B18: 11 | C18: Monitor | D18: 10
C19: TOTAL | D19: 27

Sheet Escolas
A2: Nº | B2: Escolas | C2: Municípios | D2: Total geral de alunos | E2: Quantidade de Gestores | F2: Quantidade de Coordenadores de Área | G2: Quantidade de Coordenadores de Ensino | H2: Professores de Educação Física | I2: Quantidade de Assistentes Sociais e Psicólogos | J2: Localização/Endereço | K2: Quadra | L2: Sala de Informática
A3: 1 | B3: Escola Craveiro Costa | C3: Cruzeiro do Sul | D3: 709 | E3: 1 | F3: 4 | G3: 1 | H3: 1 | I3: 0
A4: 2 | B4: Escola Dom Henrique Ruht | C4: Cruzeiro do Sul | D4: 868 | E4: 1 | F4: 4 | G4: 1 | H4: 1 | I4: 0
A5: 3 | B5: Escola Flodoardo Cabral | C5: Cruzeiro do Sul | D5: 883 | E5: 1 | F5: 4 | G5: 1 | H5: 1 | I5: 0
A6: 4 | B6: Escola Boa União Ensino Jovem | C6: Rio Branco | D6: 360 | E6: 1 | F6: 4 | G6: 1 | H6: 1 | I6: 0 | J6: Rua Três de Agosto, n° 38, Boa União - Sobral. | K6: SIM | L6: SIM
A7: 5 | B7: Colégio Estadual Barão do Rio Branco | C7: Rio Branco | D7: 761 | E7: 1 | F7: 4 | G7: 1 | H7: 1 | I7: 0 | J7: Avenida Getúlio Vargas, n° 443 - Centro. | K7: SIM | L7: SIM
A8: 6 | B8: Escola Dr. João Batista Aguiar | C8: Rio Branco | D8: 441 | E8: 1 | F8: 4 | G8: 1 | H8: 1 | I8: 0 | J8: Rua Aderbal Brasil da Silva, n° 310 - Bairro Manoel Julião. | K8: SIM | L8: SIM
A9: 7 | B9: Escola Glória Perez | C9: Rio Branco | D9: 440 | E9: 1 | F9: 4 | G9: 1 | H9: 1 | I9: 0 | J9: Avenida Brasil, n° 85, Xavier Maia - Bairro Placas. | K9: SIM | L9: SIM
A10: 8 | B10: Escola Humberto Soares da Costa | C10: Rio Branco | D10: 397 | E10: 1 | F10: 4 | G10: 1 | H10: 1 | I10: 0 | J10: Rua Riachuelo, S/N° - Bairro José Augusto. | K10: SIM | L10: SIM
A11: 9 | B11: Instituto de Educação Lourenço Filho | C11: Rio Branco | D11: 430 | E11: 1 | F11: 4 | G11: 1 | H11: 1 | I11: 0 | J11: Avenida Getúlio Vargas, n° 2855 - Bairro Bosque. | K11: SIM | L11: SIM
A12: 10 | B12: Escola Ester Maia de Oliveira | C12: Rio Branco | D12: 172 | E12: 1 | F12: 4 | G12: 1 | H12: 1 | I12: 0 | J12: Avenida Jorge Cardoso, S/N° - Cidade do Povo. | K12: SIM | L12: SIM
A13: 11 | B13: Escola Jornalista Armando Nogueira | C13: Rio Branco | D13: 327 | E13: 1 | F13: 4 | G13: 1 | H13: 1 | I13: 0 | J13: Estrada Dias Martins, n° 1494 - Distrito Insdustrial. | K13: SIM | L13: SIM
A14: 12 | B14: Escola José Ribamar Batista | C14: Rio Branco | D14: 538 | E14: 1 | F14: 4 | G14: 1 | H14: 2 | I14: 0 | J14: Rua Rio Grande do Sul, 2570 - Bairro Aeroporto Velho. | K14: SIM | L14: SIM
A15: 13 | B15: Escola Prof. Pedro Martinello | C15: Rio Branco | D15: 381 | E15: 1 | F15: 4 | G15: 1 | H15: 1 | I15: 0 | J15: Avenida Antônio Pessoa Jucá, S/N - Bairro Tancredo Neves. | K15: SIM | L15: SIM
A16: 14 | B16: Escola Sebastião Pedrosa | C16: Rio Branco | D16: 409 | E16: 1 | F16: 4 | G16: 1 | H16: 2 | I16: 0 | J16: Travessa Comara, n° 101 - Bairro Comara. | K16: SIM | L16: SIM
A17: Total | D17: =SUM(D3:D16) -> 7116 | E17: =SUM(E3:E16) -> 14 | F17: =SUM(F3:F16) -> 56 | G17: =SUM(G3:G16) -> 14 | H17: =SUM(H3:H16) -> 16 | I17: =SUM(I3:I16) -> 0
